bashsmash
